superglue/__init__.py
superglue/__main__.py
superglue/cli/__init__.py
superglue/cli/base.py
superglue/cli/commands.py
superglue/cli/messages.py
superglue/cli/utils.py
superglue/cli/validation.py
superglue/core/components/base.py
superglue/core/components/component_list.py
superglue/core/components/files.py
superglue/core/components/job.py
superglue/core/components/makefile.py
superglue/core/components/module.py
superglue/core/components/project.py
superglue/core/components/tests.py
superglue/environment/config.py
superglue/environment/variables.py
superglue/templates/__init__.py
superglue/templates/conftest.template.py
superglue/templates/job_config.template.yml
superglue/templates/job_test.template.py.txt
superglue/templates/main.template.py
superglue/templates/makefile
superglue/templates/module_test.template.py.txt
superglue/templates/template.env
superglue/templates/template.gitignore
superglue-0.20.0.dist-info/LICENSE
superglue-0.20.0.dist-info/METADATA
superglue-0.20.0.dist-info/WHEEL
superglue-0.20.0.dist-info/entry_points.txt
superglue-0.20.0.dist-info/top_level.txt
superglue-0.20.0.dist-info/RECORD
