Metadata-Version: 2.1
Name: superglue
Version: 0.20.0
Requires-Python: >=3.10.5
License-File: LICENSE
Requires-Dist: python-dotenv (==0.20.0)
Requires-Dist: pyaml (==21.10.1)
Requires-Dist: boto3 (==1.20.49)
Requires-Dist: Jinja2 (==3.0.3)
Requires-Dist: prettytable (==3.5.0)
Provides-Extra: dev
Requires-Dist: setuptools (==63.1.0) ; extra == 'dev'
Requires-Dist: build (==0.8.0) ; extra == 'dev'
Requires-Dist: python-semantic-release (==7.29.4) ; extra == 'dev'
Requires-Dist: pytest (==7.1.2) ; extra == 'dev'
Requires-Dist: black (==22.6.0) ; extra == 'dev'
Requires-Dist: pytest-dotenv (==0.5.2) ; extra == 'dev'
